{
    "Carpenter_ChangeAppearance": "Change Appearance",
    "AGO_LegacyRandomization": "Use Legacy Randomization",
    "AGO_LegacyRandomization_Tooltip": "Make random choices in a way that often repeats patterns. Most players should keep this disabled.",
    "Item_CantBeUsedHere": "This item can't be used here.",
    "NextPage": "Next page",
    "PreviousPage": "Previous page",
    "TextSignEntry": "Enter sign text",
    "Chat_RaceStarting": "The next race is starting soon...",
    "Chat_GuessRacer_1": "{0} thinks {1} is going to win the race...",
    "Chat_GuessRacer_2": "{0} will be seeing {1} at the finish line!",
    "Chat_GuessRacer_3": "{0} is hoping {1} pulls off a first place finish!",
    "Chat_GuessRacer_4": "{0} is rooting for {1}!",
    "Chat_GuessRacer_5": "{0} is Team {1}!",
    "Chat_GuessRacer_6": "{0} thinks {1} is a sure bet!",
    "Chat_GuessRacer_7": "{0} is cheering for {1}!",
    "Chat_GuessRacer_8": "{0}'s going 'all in' on {1}!",
    "Chat_GuessRacer_9": "{0} is betting big on {1}!",
    "Chat_GuessRacer_10": "{0} is sure {1}'s gonna win!",
    "Chat_RaceSabotage_1": "There's a rumor that the next race is rigged...",
    "Chat_RaceSabotage_2": "Maniacal laughter was heard behind Sandy's Oasis...",
    "Chat_RaceSabotage_3": "The fix is in...",
    "Chat_RaceSabotage_4": "The race track is looking a little slippery...",
    "Chat_RaceSabotage_5": "The little racers seem nervous about the next race...",
    "Chat_RaceWinners_Zero": "{0} has won the race!",
    "Chat_RaceWinners_One": "{0} has won the race! Congratulations {1}!",
    "Chat_RaceWinners_Two": "{0} has won the race! Congratulations {1} and {2}!",
    "Chat_RaceWinners_Many": "{0} has won the race! Congratulations",
    "Chat_RaceWinners_List": "{0},",
    "Chat_RaceWinners_Final": "and {0}!",
    "Chat_CalicoStatue_Activated": "Calico Statue: {0}",
    "Tomorrow": "Tomorrow...",
    "Chat_HardModeSkullCaveActivated": "{0} has removed an ancient magi-seal of protection in the Skull Cavern. Tonight, powerful monsters will ascend from the deep...",
    "Chat_HardModeSkullCaveDeactivated": "{0} has restored an ancient magi-seal of protection in the Skull Cavern. Tomorrow, it will return to normal...",
    "BirthdayOrder": "{1} {0}"
}